tcgplayer_api/VERSION
tcgplayer_api/__init__.py
tcgplayer_api/auth.py
tcgplayer_api/client.py
tcgplayer_api/utils.py
tcgplayer_api-0.0.1.dist-info/LICENSE
tcgplayer_api-0.0.1.dist-info/METADATA
tcgplayer_api-0.0.1.dist-info/WHEEL
tcgplayer_api-0.0.1.dist-info/top_level.txt
tcgplayer_api-0.0.1.dist-info/RECORD
