Metadata-Version: 2.1
Name: tcgplayer-api
Version: 0.0.1
Summary: A Python client library for the TCGPlayer API.
Home-page: https://github.com/zaxr/tcgplayer-api-client-python
Author: Zax Rosenberg
Author-email: zaxr@protonmail.com
License: UNKNOWN
Keywords: mtg magic the gathering tcg player api client
Platform: UNKNOWN
Classifier: Development Status :: 2 - Pre-Alpha
Classifier: Intended Audience :: Developers
Classifier: Natural Language :: English
Classifier: Programming Language :: Python :: 3
Classifier: Programming Language :: Python :: 3.6
Classifier: Programming Language :: Python :: 3.7
Classifier: Programming Language :: Python :: 3.8
Requires-Python: >=3.6
Requires-Dist: requests
Provides-Extra: dev
Requires-Dist: pytest ; extra == 'dev'
Requires-Dist: pytest-cov ; extra == 'dev'
Requires-Dist: m2r ; extra == 'dev'
Requires-Dist: setuptools (>=30.4) ; extra == 'dev'
Requires-Dist: Sphinx (~=2.0) ; extra == 'dev'
Requires-Dist: sphinxcontrib-apidoc (~=0.3.0) ; extra == 'dev'
Requires-Dist: sphinx-rtd-theme ; extra == 'dev'
Requires-Dist: pre-commit ; extra == 'dev'
Requires-Dist: tox ; extra == 'dev'
Provides-Extra: docs
Requires-Dist: m2r ; extra == 'docs'
Requires-Dist: setuptools (>=30.4) ; extra == 'docs'
Requires-Dist: Sphinx (~=2.0) ; extra == 'docs'
Requires-Dist: sphinxcontrib-apidoc (~=0.3.0) ; extra == 'docs'
Requires-Dist: sphinx-rtd-theme ; extra == 'docs'
Provides-Extra: test
Requires-Dist: pytest ; extra == 'test'
Requires-Dist: pytest-cov ; extra == 'test'
